CONTRIBUTING.rst
MANIFEST.in
README.rst
pg_view.py
requirements.txt
setup.py
pg_view.egg-info/PKG-INFO
pg_view.egg-info/SOURCES.txt
pg_view.egg-info/dependency_links.txt
pg_view.egg-info/entry_points.txt
pg_view.egg-info/requires.txt
pg_view.egg-info/top_level.txt