Metadata-Version: 1.1
Name: pg-view
Version: 1.4.0
Summary: PostgreSQL Activity View Utility
Home-page: https://github.com/zalando/pg_view
Author: Oleksii Kliukin
Author-email: oleksii.kliukin@zalando.de
License: Apache License 2.0
Keywords: postgres postgresql pg database
Platform: UNKNOWN
Classifier: Development Status :: 5 - Production/Stable
Classifier: Environment :: Console
Classifier: Intended Audience :: Developers
Classifier: Intended Audience :: System Administrators
Classifier: License :: OSI Approved :: Apache Software License
Classifier: Operating System :: POSIX :: Linux
Classifier: Programming Language :: Python
Classifier: Programming Language :: Python :: 2.7
Classifier: Programming Language :: Python :: 3.4
Classifier: Programming Language :: Python :: Implementation :: CPython
Classifier: Topic :: Database
